Metadata-Version: 2.1
Name: niva-package
Version: 0.4
Summary: A description of your project
Requires-Python: >=3.6
License-File: licence .txt
